aco.py
aco/__init__.py
aco/aco.py
aco/sound.py
ACOio-0.2.2.dist-info/LICENSE
ACOio-0.2.2.dist-info/METADATA
ACOio-0.2.2.dist-info/WHEEL
ACOio-0.2.2.dist-info/top_level.txt
ACOio-0.2.2.dist-info/RECORD
